magic_list/__init__.py
magic_list/prelude.py
magic_list/prelude.pyi
magic_list/py.typed
magic_list-2.4.0.dist-info/LICENSE
magic_list-2.4.0.dist-info/METADATA
magic_list-2.4.0.dist-info/WHEEL
magic_list-2.4.0.dist-info/top_level.txt
magic_list-2.4.0.dist-info/RECORD
