Metadata-Version: 2.1
Name: magic-list
Version: 2.4.0
Summary: Magic List is a module that extends the built-in list type.
Author-email: Qexat <contact@qexat.com>
License: MIT License
Project-URL: documentation, https://qexat.github.io/magic-list/
Project-URL: repository, https://github.com/qexat/magic-list
Keywords: collections,list,built-in,extension
Classifier: License :: OSI Approved :: MIT License
Classifier: Programming Language :: Python :: 3
Classifier: Development Status :: 5 - Production/Stable
Classifier: Intended Audience :: Developers
Classifier: Topic :: Software Development :: Libraries :: Python Modules
Classifier: Topic :: Utilities
Classifier: Typing :: Typed
Requires-Python: >=3.9
License-File: LICENSE
Provides-Extra: dev
Requires-Dist: build <2.0,>=1.2 ; extra == 'dev'
Requires-Dist: coverage <8.0,>=7.4 ; extra == 'dev'
Requires-Dist: pdoc <15.0,>=14.4 ; extra == 'dev'
Requires-Dist: pre-commit <4.0,>=3.7 ; extra == 'dev'
Requires-Dist: pytest <8.2,>=7.4 ; extra == 'dev'
Requires-Dist: pyright <2.0,>=1.1 ; extra == 'dev'
Requires-Dist: ruff <1.0,>=0.4 ; extra == 'dev'
Requires-Dist: twine <6.0,>=5.0 ; extra == 'dev'
Requires-Dist: typing-extensions >=4.11 ; extra == 'dev'
